periodogram/__init__.py
periodogram/estimator.py
periodogram/normalization.py
periodogram/periodogram.py
periodogram/utils.py
periodogram/version.py
periodogram/window.py
periodogram-0.0.13.dist-info/METADATA
periodogram-0.0.13.dist-info/WHEEL
periodogram-0.0.13.dist-info/top_level.txt
periodogram-0.0.13.dist-info/RECORD
