Metadata-Version: 2.1
Name: periodogram
Version: 0.0.13
Summary: Simple periodogram manipulation in Python.
Home-page: https://github.com/danhey/periodogram
Author: Daniel Hey
Classifier: Intended Audience :: Developers
Classifier: Intended Audience :: Science/Research
Classifier: Operating System :: OS Independent
Classifier: Programming Language :: Python
Requires-Dist: astropy
Requires-Dist: numpy
Requires-Dist: matplotlib
